omnitools/__init__.py
omnitools/xdatetime.py
omnitools/xdebug.py
omnitools/xdecorator.py
omnitools/xftp.py
omnitools/xhash.py
omnitools/xhtml.py
omnitools/ximage.py
omnitools/xinspect.py
omnitools/xjs.py
omnitools/xmask.py
omnitools/xmisc.py
omnitools/xos.py
omnitools/xpip.py
omnitools/xrng.py
omnitools/xstdin.py
omnitools/xstdout.py
omnitools/xtrace.py
omnitools/xtype.py
omnitools/__metadata__/DISCLAIMER.md
omnitools/__metadata__/LICENSE
omnitools/__metadata__/README.md
omnitools/__metadata__/__init__.py
omnitools/__metadata__/requirements.txt
omnitools/xencode/__init__.py
omnitools/xencode/b64.py
omnitools/xencode/file.py
omnitools/xencode/utf8.py
omnitools/xfile/__init__.py
omnitools/xfile/file.py
omnitools/xfile/path.py
omnitools/xfile/tree.py
omnitools/xsys/__init__.py
omnitools/xsys/pyver.py
omnitools/xurl/__init__.py
omnitools/xurl/path.py
omnitools-0.0.267.dist-info/METADATA
omnitools-0.0.267.dist-info/WHEEL
omnitools-0.0.267.dist-info/top_level.txt
omnitools-0.0.267.dist-info/RECORD
